rate_control/__init__.py
rate_control/_bucket_group.py
rate_control/_buckets/__init__.py
rate_control/_buckets/_base/__init__.py
rate_control/_buckets/_base/_abc.py
rate_control/_buckets/_base/_base_rate.py
rate_control/_buckets/_base/_capacity_updating.py
rate_control/_buckets/_base/_token_based.py
rate_control/_buckets/_base/_windowed.py
rate_control/_buckets/_fixed_window_counter.py
rate_control/_buckets/_leaky_bucket.py
rate_control/_buckets/_sliding_window_log.py
rate_control/_controllers/__init__.py
rate_control/_controllers/_abc.py
rate_control/_controllers/_bucket_based.py
rate_control/_controllers/_noop_controller.py
rate_control/_controllers/_rate_limiter.py
rate_control/_controllers/_scheduler.py
rate_control/_enums/__init__.py
rate_control/_enums/_duration.py
rate_control/_enums/_priority.py
rate_control/_enums/_state.py
rate_control/_errors.py
rate_control/_helpers/__init__.py
rate_control/_helpers/_context_aware.py
rate_control/_helpers/_mk_repr.py
rate_control/_helpers/_protocols.py
rate_control/_helpers/_request.py
rate_control/_helpers/_validation.py
rate_control/py.typed
rate_control/queues/__init__.py
rate_control/queues/_abc.py
rate_control/queues/_fifo.py
rate_control/queues/_lifo.py
rate_control/queues/_priority.py
rate_control-4.1.1.dist-info/LICENSE
rate_control-4.1.1.dist-info/METADATA
rate_control-4.1.1.dist-info/WHEEL
rate_control-4.1.1.dist-info/RECORD
