Metadata-Version: 2.1
Name: rate-control
Version: 4.1.1
Summary: Versatile rate controlling in Python
Home-page: https://github.com/corentin-regent/rate-control
License: MIT
Keywords: async,rate limit,schedule,throttle,token bucket
Author: Corentin Régent
Author-email: corentin.regent.pro@gmail.com
Requires-Python: >=3.8,<4.0
Classifier: Development Status :: 4 - Beta
Classifier: Framework :: AnyIO
Classifier: Framework :: AsyncIO
Classifier: Framework :: Trio
Classifier: License :: OSI Approved :: MIT License
Classifier: Operating System :: OS Independent
Classifier: Programming Language :: Python
Classifier: Programming Language :: Python :: 3
Classifier: Programming Language :: Python :: 3.8
Classifier: Programming Language :: Python :: 3.9
Classifier: Programming Language :: Python :: 3.10
Classifier: Programming Language :: Python :: 3.11
Classifier: Programming Language :: Python :: 3.12
Classifier: Typing :: Typed
Requires-Dist: anyio (>=4.0.0,<5.0.0)
Requires-Dist: typing_extensions (>=4.4.0,<5.0.0) ; python_version < "3.12"
Project-URL: Changelog, https://rate-control.readthedocs.io/en/latest/changelog.html
Project-URL: Documentation, https://rate-control.readthedocs.io/
Project-URL: Repository, https://github.com/corentin-regent/rate-control
